{
  "variants": {
    "facing=down,turned_on=false": {
      "model": "mangomilk_building:block/brass_floodlight/block"
    },
    "facing=down,turned_on=true": {
      "model": "mangomilk_building:block/brass_floodlight/block_on"
    },
    "facing=east,turned_on=false": {
      "model": "mangomilk_building:block/brass_floodlight/block",
      "y": 90
    },
    "facing=east,turned_on=true": {
      "model": "mangomilk_building:block/brass_floodlight/block_on",
      "y": 90
    },
    "facing=north,turned_on=false": {
      "model": "mangomilk_building:block/brass_floodlight/block"
    },
    "facing=north,turned_on=true": {
      "model": "mangomilk_building:block/brass_floodlight/block_on"
    },
    "facing=south,turned_on=false": {
      "model": "mangomilk_building:block/brass_floodlight/block",
      "y": 180
    },
    "facing=south,turned_on=true": {
      "model": "mangomilk_building:block/brass_floodlight/block_on",
      "y": 180
    },
    "facing=up,turned_on=false": {
      "model": "mangomilk_building:block/brass_floodlight/block"
    },
    "facing=up,turned_on=true": {
      "model": "mangomilk_building:block/brass_floodlight/block_on"
    },
    "facing=west,turned_on=false": {
      "model": "mangomilk_building:block/brass_floodlight/block",
      "y": 270
    },
    "facing=west,turned_on=true": {
      "model": "mangomilk_building:block/brass_floodlight/block_on",
      "y": 270
    }
  }
}